data533_superwoman/__init__.py
data533_superwoman/administer/__init__.py
data533_superwoman/administer/account.py
data533_superwoman/administer/inventory.py
data533_superwoman/administer/summary.py
data533_superwoman/customer/__init__.py
data533_superwoman/customer/customer_function.py
data533_superwoman/customer/members.py
data533_superwoman/customer/transactions.py
data533_superwoman-0.0.1.dist-info/METADATA
data533_superwoman-0.0.1.dist-info/WHEEL
data533_superwoman-0.0.1.dist-info/top_level.txt
data533_superwoman-0.0.1.dist-info/RECORD
